celigo_pipeline_core/__init__.py
celigo_pipeline_core/celigo_orchestration.py
celigo_pipeline_core/notifcations.py
celigo_pipeline_core/postgres_db_functions.py
celigo_pipeline_core/bin/__init__.py
celigo_pipeline_core/bin/celigo_pipeline_core_cli.py
celigo_pipeline_core/bin/run_dir_cli.py
celigo_pipeline_core/celigo_single_image/__init__.py
celigo_pipeline_core/celigo_single_image/celigo_image.py
celigo_pipeline_core/celigo_single_image/celigo_single_image_core.py
celigo_pipeline_core/celigo_single_image/celigo_six_well_core.py
celigo_pipeline_core/pipelines/6_well_confluency_cellprofilerpipeline_v2.0.cppipe
celigo_pipeline_core/pipelines/6_well_confluency_cellprofilerpipeline_v2.1.cppipe
celigo_pipeline_core/pipelines/6_well_rescaleandcrop_cellprofilerpipeline_v2.0.cppipe
celigo_pipeline_core/pipelines/96_well_colony_pipeline.cppipe
celigo_pipeline_core/pipelines/96_well_colony_pipeline_v2.cppipe
celigo_pipeline_core/pipelines/96_well_colony_pipeline_v_0.1.cppipe
celigo_pipeline_core/pipelines/__init__.py
celigo_pipeline_core/pipelines/colony_morphology.model
celigo_pipeline_core/pipelines/colonymorphology.model
celigo_pipeline_core/pipelines/rescale_pipeline.cppipe
celigo_pipeline_core/templates/6_well_ilastik_template.j2
celigo_pipeline_core/templates/96_well_pipeline_v1.0_tempalate.j2
celigo_pipeline_core/templates/96_well_pipeline_v2_tempalate.j2
celigo_pipeline_core/templates/cellprofiler_template.j2
celigo_pipeline_core/templates/ilastik_template.j2
celigo_pipeline_core/templates/resize_cellprofiler_template.j2
celigo_pipeline_core-3.0.0.dist-info/DESCRIPTION.rst
celigo_pipeline_core-3.0.0.dist-info/METADATA
celigo_pipeline_core-3.0.0.dist-info/RECORD
celigo_pipeline_core-3.0.0.dist-info/WHEEL
celigo_pipeline_core-3.0.0.dist-info/entry_points.txt
celigo_pipeline_core-3.0.0.dist-info/metadata.json
celigo_pipeline_core-3.0.0.dist-info/top_level.txt
